{"program":"XEI Living Company Executive Series","version":"1.0.0","status":"Production Complete / Executive Approved","governingSentence":"We are not demonstrating software. We are allowing an executive to experience the future of building companies.","category":"Xen is the operating system for designing Living Companies.","entrypoints":{"premiere":"index.html","series":"series.html"},"modules":[{"id":"XEI-001","name":"Xenesis Executive Premiere","status":"production-complete"},{"id":"XEI-002","name":"Living Company Blueprint Session","status":"production-complete"},{"id":"XEI-003","name":"Executive Transformation Proposal","status":"production-complete"},{"id":"XEI-004","name":"First Living Department Deployment","status":"production-complete"},{"id":"XEI-005","name":"Living Manual Runtime","status":"production-complete"},{"id":"XEI-006","name":"Executive Memory & Decision Intelligence","status":"production-complete"},{"id":"XEI-007","name":"Enterprise Propagation Engine","status":"production-complete"},{"id":"XEI-008","name":"Living Company Dashboard","status":"production-complete"},{"id":"XEI-009","name":"Executive Command Center","status":"production-complete"},{"id":"XEI-010","name":"Enterprise Rollout & Multi-Company Orchestration","status":"production-complete"}],"runtime":{"premiere":"src/app.js","series":"src/series.js","design":["src/styles.css","src/series.css"],"persistence":["xei-001-gold-master","xei-series-v1"],"validation":"tests/validate.mjs"},"certificationTruth":"Repository-controlled implementation is complete. Physical iPhone Safari, desktop browser, deployed performance, and live neural voice acceptance remain external environment evidence gates."}